{
	"arrowColors": null,
	"camOffset": {
		"x": -140,
		"y": 120
	},
	"globalOffset": {
		"x": 820,
		"y": 610
	},
	"healthbarColor": "#6161C2",
	"flipX": true,
	"anims": [
		{
			"indices": null,
			"x": 0,
			"y": 0,
			"anim": "sonic idle",
			"loop": true,
			"name": "idle",
			"framerate": 21
		},
		{
			"indices": null,
			"x": 0,
			"y": 0,
			"anim": "sonic sing right",
			"loop": false,
			"name": "singRIGHT",
			"framerate": 24
		},
		{
			"indices": null,
			"x": 0,
			"y": 0,
			"anim": "sonic sing down",
			"loop": false,
			"name": "singDOWN",
			"framerate": 24
		},
		{
			"indices": null,
			"x": 0,
			"y": 0,
			"anim": "dialogue ",
			"loop": false,
			"name": "cool funni talk real?",
			"framerate": 24
		},
		{
			"indices": null,
			"x": 0,
			"y": 0,
			"anim": "sonic left sing",
			"loop": false,
			"name": "singLEFT",
			"framerate": 24
		},
		{
			"indices": null,
			"x": 0,
			"y": 0,
			"anim": "sonic sing up",
			"loop": false,
			"name": "singUP",
			"framerate": 24
		}
	],
	"danceSteps": [
		"idle"
	],
	"antialiasing": false,
	"healthIconSteps": [
		[
			20,
			0
		],
		[
			0,
			1
		]
	],
	"scale": 6
}